{
    "timeLimit": 30,
    "questions": [
        {
            "id": 1,
            "question": "Dummy Question 1 for Applications Differentiation: Which of the following is correct?",
            "options": [
                "Option A for Applications Differentiation",
                "Option B for Applications Differentiation (Correct)",
                "Option C for Applications Differentiation",
                "Option D for Applications Differentiation"
            ],
            "correctIndex": 1,
            "explanation": "This is an auto-generated dummy explanation for Applications Differentiation."
        },
        {
            "id": 2,
            "question": "Dummy Question 2 for Applications Differentiation: Which of the following is correct?",
            "options": [
                "Option A for Applications Differentiation",
                "Option B for Applications Differentiation (Correct)",
                "Option C for Applications Differentiation",
                "Option D for Applications Differentiation"
            ],
            "correctIndex": 1,
            "explanation": "This is an auto-generated dummy explanation for Applications Differentiation."
        },
        {
            "id": 3,
            "question": "Dummy Question 3 for Applications Differentiation: Which of the following is correct?",
            "options": [
                "Option A for Applications Differentiation",
                "Option B for Applications Differentiation (Correct)",
                "Option C for Applications Differentiation",
                "Option D for Applications Differentiation"
            ],
            "correctIndex": 1,
            "explanation": "This is an auto-generated dummy explanation for Applications Differentiation."
        },
        {
            "id": 4,
            "question": "Dummy Question 4 for Applications Differentiation: Which of the following is correct?",
            "options": [
                "Option A for Applications Differentiation",
                "Option B for Applications Differentiation (Correct)",
                "Option C for Applications Differentiation",
                "Option D for Applications Differentiation"
            ],
            "correctIndex": 1,
            "explanation": "This is an auto-generated dummy explanation for Applications Differentiation."
        },
        {
            "id": 5,
            "question": "Dummy Question 5 for Applications Differentiation: Which of the following is correct?",
            "options": [
                "Option A for Applications Differentiation",
                "Option B for Applications Differentiation (Correct)",
                "Option C for Applications Differentiation",
                "Option D for Applications Differentiation"
            ],
            "correctIndex": 1,
            "explanation": "This is an auto-generated dummy explanation for Applications Differentiation."
        },
        {
            "id": 6,
            "question": "Dummy Question 6 for Applications Differentiation: Which of the following is correct?",
            "options": [
                "Option A for Applications Differentiation",
                "Option B for Applications Differentiation (Correct)",
                "Option C for Applications Differentiation",
                "Option D for Applications Differentiation"
            ],
            "correctIndex": 1,
            "explanation": "This is an auto-generated dummy explanation for Applications Differentiation."
        },
        {
            "id": 7,
            "question": "Dummy Question 7 for Applications Differentiation: Which of the following is correct?",
            "options": [
                "Option A for Applications Differentiation",
                "Option B for Applications Differentiation (Correct)",
                "Option C for Applications Differentiation",
                "Option D for Applications Differentiation"
            ],
            "correctIndex": 1,
            "explanation": "This is an auto-generated dummy explanation for Applications Differentiation."
        },
        {
            "id": 8,
            "question": "Dummy Question 8 for Applications Differentiation: Which of the following is correct?",
            "options": [
                "Option A for Applications Differentiation",
                "Option B for Applications Differentiation (Correct)",
                "Option C for Applications Differentiation",
                "Option D for Applications Differentiation"
            ],
            "correctIndex": 1,
            "explanation": "This is an auto-generated dummy explanation for Applications Differentiation."
        },
        {
            "id": 9,
            "question": "Dummy Question 9 for Applications Differentiation: Which of the following is correct?",
            "options": [
                "Option A for Applications Differentiation",
                "Option B for Applications Differentiation (Correct)",
                "Option C for Applications Differentiation",
                "Option D for Applications Differentiation"
            ],
            "correctIndex": 1,
            "explanation": "This is an auto-generated dummy explanation for Applications Differentiation."
        },
        {
            "id": 10,
            "question": "Dummy Question 10 for Applications Differentiation: Which of the following is correct?",
            "options": [
                "Option A for Applications Differentiation",
                "Option B for Applications Differentiation (Correct)",
                "Option C for Applications Differentiation",
                "Option D for Applications Differentiation"
            ],
            "correctIndex": 1,
            "explanation": "This is an auto-generated dummy explanation for Applications Differentiation."
        },
        {
            "id": 11,
            "question": "Dummy Question 11 for Applications Differentiation: Which of the following is correct?",
            "options": [
                "Option A for Applications Differentiation",
                "Option B for Applications Differentiation (Correct)",
                "Option C for Applications Differentiation",
                "Option D for Applications Differentiation"
            ],
            "correctIndex": 1,
            "explanation": "This is an auto-generated dummy explanation for Applications Differentiation."
        },
        {
            "id": 12,
            "question": "Dummy Question 12 for Applications Differentiation: Which of the following is correct?",
            "options": [
                "Option A for Applications Differentiation",
                "Option B for Applications Differentiation (Correct)",
                "Option C for Applications Differentiation",
                "Option D for Applications Differentiation"
            ],
            "correctIndex": 1,
            "explanation": "This is an auto-generated dummy explanation for Applications Differentiation."
        },
        {
            "id": 13,
            "question": "Dummy Question 13 for Applications Differentiation: Which of the following is correct?",
            "options": [
                "Option A for Applications Differentiation",
                "Option B for Applications Differentiation (Correct)",
                "Option C for Applications Differentiation",
                "Option D for Applications Differentiation"
            ],
            "correctIndex": 1,
            "explanation": "This is an auto-generated dummy explanation for Applications Differentiation."
        },
        {
            "id": 14,
            "question": "Dummy Question 14 for Applications Differentiation: Which of the following is correct?",
            "options": [
                "Option A for Applications Differentiation",
                "Option B for Applications Differentiation (Correct)",
                "Option C for Applications Differentiation",
                "Option D for Applications Differentiation"
            ],
            "correctIndex": 1,
            "explanation": "This is an auto-generated dummy explanation for Applications Differentiation."
        },
        {
            "id": 15,
            "question": "Dummy Question 15 for Applications Differentiation: Which of the following is correct?",
            "options": [
                "Option A for Applications Differentiation",
                "Option B for Applications Differentiation (Correct)",
                "Option C for Applications Differentiation",
                "Option D for Applications Differentiation"
            ],
            "correctIndex": 1,
            "explanation": "This is an auto-generated dummy explanation for Applications Differentiation."
        },
        {
            "id": 16,
            "question": "Dummy Question 16 for Applications Differentiation: Which of the following is correct?",
            "options": [
                "Option A for Applications Differentiation",
                "Option B for Applications Differentiation (Correct)",
                "Option C for Applications Differentiation",
                "Option D for Applications Differentiation"
            ],
            "correctIndex": 1,
            "explanation": "This is an auto-generated dummy explanation for Applications Differentiation."
        },
        {
            "id": 17,
            "question": "Dummy Question 17 for Applications Differentiation: Which of the following is correct?",
            "options": [
                "Option A for Applications Differentiation",
                "Option B for Applications Differentiation (Correct)",
                "Option C for Applications Differentiation",
                "Option D for Applications Differentiation"
            ],
            "correctIndex": 1,
            "explanation": "This is an auto-generated dummy explanation for Applications Differentiation."
        },
        {
            "id": 18,
            "question": "Dummy Question 18 for Applications Differentiation: Which of the following is correct?",
            "options": [
                "Option A for Applications Differentiation",
                "Option B for Applications Differentiation (Correct)",
                "Option C for Applications Differentiation",
                "Option D for Applications Differentiation"
            ],
            "correctIndex": 1,
            "explanation": "This is an auto-generated dummy explanation for Applications Differentiation."
        },
        {
            "id": 19,
            "question": "Dummy Question 19 for Applications Differentiation: Which of the following is correct?",
            "options": [
                "Option A for Applications Differentiation",
                "Option B for Applications Differentiation (Correct)",
                "Option C for Applications Differentiation",
                "Option D for Applications Differentiation"
            ],
            "correctIndex": 1,
            "explanation": "This is an auto-generated dummy explanation for Applications Differentiation."
        },
        {
            "id": 20,
            "question": "Dummy Question 20 for Applications Differentiation: Which of the following is correct?",
            "options": [
                "Option A for Applications Differentiation",
                "Option B for Applications Differentiation (Correct)",
                "Option C for Applications Differentiation",
                "Option D for Applications Differentiation"
            ],
            "correctIndex": 1,
            "explanation": "This is an auto-generated dummy explanation for Applications Differentiation."
        },
        {
            "id": 21,
            "question": "Dummy Question 21 for Applications Differentiation: Which of the following is correct?",
            "options": [
                "Option A for Applications Differentiation",
                "Option B for Applications Differentiation (Correct)",
                "Option C for Applications Differentiation",
                "Option D for Applications Differentiation"
            ],
            "correctIndex": 1,
            "explanation": "This is an auto-generated dummy explanation for Applications Differentiation."
        },
        {
            "id": 22,
            "question": "Dummy Question 22 for Applications Differentiation: Which of the following is correct?",
            "options": [
                "Option A for Applications Differentiation",
                "Option B for Applications Differentiation (Correct)",
                "Option C for Applications Differentiation",
                "Option D for Applications Differentiation"
            ],
            "correctIndex": 1,
            "explanation": "This is an auto-generated dummy explanation for Applications Differentiation."
        },
        {
            "id": 23,
            "question": "Dummy Question 23 for Applications Differentiation: Which of the following is correct?",
            "options": [
                "Option A for Applications Differentiation",
                "Option B for Applications Differentiation (Correct)",
                "Option C for Applications Differentiation",
                "Option D for Applications Differentiation"
            ],
            "correctIndex": 1,
            "explanation": "This is an auto-generated dummy explanation for Applications Differentiation."
        },
        {
            "id": 24,
            "question": "Dummy Question 24 for Applications Differentiation: Which of the following is correct?",
            "options": [
                "Option A for Applications Differentiation",
                "Option B for Applications Differentiation (Correct)",
                "Option C for Applications Differentiation",
                "Option D for Applications Differentiation"
            ],
            "correctIndex": 1,
            "explanation": "This is an auto-generated dummy explanation for Applications Differentiation."
        },
        {
            "id": 25,
            "question": "Dummy Question 25 for Applications Differentiation: Which of the following is correct?",
            "options": [
                "Option A for Applications Differentiation",
                "Option B for Applications Differentiation (Correct)",
                "Option C for Applications Differentiation",
                "Option D for Applications Differentiation"
            ],
            "correctIndex": 1,
            "explanation": "This is an auto-generated dummy explanation for Applications Differentiation."
        },
        {
            "id": 26,
            "question": "Dummy Question 26 for Applications Differentiation: Which of the following is correct?",
            "options": [
                "Option A for Applications Differentiation",
                "Option B for Applications Differentiation (Correct)",
                "Option C for Applications Differentiation",
                "Option D for Applications Differentiation"
            ],
            "correctIndex": 1,
            "explanation": "This is an auto-generated dummy explanation for Applications Differentiation."
        },
        {
            "id": 27,
            "question": "Dummy Question 27 for Applications Differentiation: Which of the following is correct?",
            "options": [
                "Option A for Applications Differentiation",
                "Option B for Applications Differentiation (Correct)",
                "Option C for Applications Differentiation",
                "Option D for Applications Differentiation"
            ],
            "correctIndex": 1,
            "explanation": "This is an auto-generated dummy explanation for Applications Differentiation."
        },
        {
            "id": 28,
            "question": "Dummy Question 28 for Applications Differentiation: Which of the following is correct?",
            "options": [
                "Option A for Applications Differentiation",
                "Option B for Applications Differentiation (Correct)",
                "Option C for Applications Differentiation",
                "Option D for Applications Differentiation"
            ],
            "correctIndex": 1,
            "explanation": "This is an auto-generated dummy explanation for Applications Differentiation."
        },
        {
            "id": 29,
            "question": "Dummy Question 29 for Applications Differentiation: Which of the following is correct?",
            "options": [
                "Option A for Applications Differentiation",
                "Option B for Applications Differentiation (Correct)",
                "Option C for Applications Differentiation",
                "Option D for Applications Differentiation"
            ],
            "correctIndex": 1,
            "explanation": "This is an auto-generated dummy explanation for Applications Differentiation."
        },
        {
            "id": 30,
            "question": "Dummy Question 30 for Applications Differentiation: Which of the following is correct?",
            "options": [
                "Option A for Applications Differentiation",
                "Option B for Applications Differentiation (Correct)",
                "Option C for Applications Differentiation",
                "Option D for Applications Differentiation"
            ],
            "correctIndex": 1,
            "explanation": "This is an auto-generated dummy explanation for Applications Differentiation."
        },
        {
            "id": 31,
            "question": "Dummy Question 31 for Applications Differentiation: Which of the following is correct?",
            "options": [
                "Option A for Applications Differentiation",
                "Option B for Applications Differentiation (Correct)",
                "Option C for Applications Differentiation",
                "Option D for Applications Differentiation"
            ],
            "correctIndex": 1,
            "explanation": "This is an auto-generated dummy explanation for Applications Differentiation."
        },
        {
            "id": 32,
            "question": "Dummy Question 32 for Applications Differentiation: Which of the following is correct?",
            "options": [
                "Option A for Applications Differentiation",
                "Option B for Applications Differentiation (Correct)",
                "Option C for Applications Differentiation",
                "Option D for Applications Differentiation"
            ],
            "correctIndex": 1,
            "explanation": "This is an auto-generated dummy explanation for Applications Differentiation."
        },
        {
            "id": 33,
            "question": "Dummy Question 33 for Applications Differentiation: Which of the following is correct?",
            "options": [
                "Option A for Applications Differentiation",
                "Option B for Applications Differentiation (Correct)",
                "Option C for Applications Differentiation",
                "Option D for Applications Differentiation"
            ],
            "correctIndex": 1,
            "explanation": "This is an auto-generated dummy explanation for Applications Differentiation."
        },
        {
            "id": 34,
            "question": "Dummy Question 34 for Applications Differentiation: Which of the following is correct?",
            "options": [
                "Option A for Applications Differentiation",
                "Option B for Applications Differentiation (Correct)",
                "Option C for Applications Differentiation",
                "Option D for Applications Differentiation"
            ],
            "correctIndex": 1,
            "explanation": "This is an auto-generated dummy explanation for Applications Differentiation."
        },
        {
            "id": 35,
            "question": "Dummy Question 35 for Applications Differentiation: Which of the following is correct?",
            "options": [
                "Option A for Applications Differentiation",
                "Option B for Applications Differentiation (Correct)",
                "Option C for Applications Differentiation",
                "Option D for Applications Differentiation"
            ],
            "correctIndex": 1,
            "explanation": "This is an auto-generated dummy explanation for Applications Differentiation."
        },
        {
            "id": 36,
            "question": "Dummy Question 36 for Applications Differentiation: Which of the following is correct?",
            "options": [
                "Option A for Applications Differentiation",
                "Option B for Applications Differentiation (Correct)",
                "Option C for Applications Differentiation",
                "Option D for Applications Differentiation"
            ],
            "correctIndex": 1,
            "explanation": "This is an auto-generated dummy explanation for Applications Differentiation."
        },
        {
            "id": 37,
            "question": "Dummy Question 37 for Applications Differentiation: Which of the following is correct?",
            "options": [
                "Option A for Applications Differentiation",
                "Option B for Applications Differentiation (Correct)",
                "Option C for Applications Differentiation",
                "Option D for Applications Differentiation"
            ],
            "correctIndex": 1,
            "explanation": "This is an auto-generated dummy explanation for Applications Differentiation."
        },
        {
            "id": 38,
            "question": "Dummy Question 38 for Applications Differentiation: Which of the following is correct?",
            "options": [
                "Option A for Applications Differentiation",
                "Option B for Applications Differentiation (Correct)",
                "Option C for Applications Differentiation",
                "Option D for Applications Differentiation"
            ],
            "correctIndex": 1,
            "explanation": "This is an auto-generated dummy explanation for Applications Differentiation."
        },
        {
            "id": 39,
            "question": "Dummy Question 39 for Applications Differentiation: Which of the following is correct?",
            "options": [
                "Option A for Applications Differentiation",
                "Option B for Applications Differentiation (Correct)",
                "Option C for Applications Differentiation",
                "Option D for Applications Differentiation"
            ],
            "correctIndex": 1,
            "explanation": "This is an auto-generated dummy explanation for Applications Differentiation."
        },
        {
            "id": 40,
            "question": "Dummy Question 40 for Applications Differentiation: Which of the following is correct?",
            "options": [
                "Option A for Applications Differentiation",
                "Option B for Applications Differentiation (Correct)",
                "Option C for Applications Differentiation",
                "Option D for Applications Differentiation"
            ],
            "correctIndex": 1,
            "explanation": "This is an auto-generated dummy explanation for Applications Differentiation."
        },
        {
            "id": 41,
            "question": "Dummy Question 41 for Applications Differentiation: Which of the following is correct?",
            "options": [
                "Option A for Applications Differentiation",
                "Option B for Applications Differentiation (Correct)",
                "Option C for Applications Differentiation",
                "Option D for Applications Differentiation"
            ],
            "correctIndex": 1,
            "explanation": "This is an auto-generated dummy explanation for Applications Differentiation."
        },
        {
            "id": 42,
            "question": "Dummy Question 42 for Applications Differentiation: Which of the following is correct?",
            "options": [
                "Option A for Applications Differentiation",
                "Option B for Applications Differentiation (Correct)",
                "Option C for Applications Differentiation",
                "Option D for Applications Differentiation"
            ],
            "correctIndex": 1,
            "explanation": "This is an auto-generated dummy explanation for Applications Differentiation."
        },
        {
            "id": 43,
            "question": "Dummy Question 43 for Applications Differentiation: Which of the following is correct?",
            "options": [
                "Option A for Applications Differentiation",
                "Option B for Applications Differentiation (Correct)",
                "Option C for Applications Differentiation",
                "Option D for Applications Differentiation"
            ],
            "correctIndex": 1,
            "explanation": "This is an auto-generated dummy explanation for Applications Differentiation."
        },
        {
            "id": 44,
            "question": "Dummy Question 44 for Applications Differentiation: Which of the following is correct?",
            "options": [
                "Option A for Applications Differentiation",
                "Option B for Applications Differentiation (Correct)",
                "Option C for Applications Differentiation",
                "Option D for Applications Differentiation"
            ],
            "correctIndex": 1,
            "explanation": "This is an auto-generated dummy explanation for Applications Differentiation."
        },
        {
            "id": 45,
            "question": "Dummy Question 45 for Applications Differentiation: Which of the following is correct?",
            "options": [
                "Option A for Applications Differentiation",
                "Option B for Applications Differentiation (Correct)",
                "Option C for Applications Differentiation",
                "Option D for Applications Differentiation"
            ],
            "correctIndex": 1,
            "explanation": "This is an auto-generated dummy explanation for Applications Differentiation."
        },
        {
            "id": 46,
            "question": "Dummy Question 46 for Applications Differentiation: Which of the following is correct?",
            "options": [
                "Option A for Applications Differentiation",
                "Option B for Applications Differentiation (Correct)",
                "Option C for Applications Differentiation",
                "Option D for Applications Differentiation"
            ],
            "correctIndex": 1,
            "explanation": "This is an auto-generated dummy explanation for Applications Differentiation."
        },
        {
            "id": 47,
            "question": "Dummy Question 47 for Applications Differentiation: Which of the following is correct?",
            "options": [
                "Option A for Applications Differentiation",
                "Option B for Applications Differentiation (Correct)",
                "Option C for Applications Differentiation",
                "Option D for Applications Differentiation"
            ],
            "correctIndex": 1,
            "explanation": "This is an auto-generated dummy explanation for Applications Differentiation."
        },
        {
            "id": 48,
            "question": "Dummy Question 48 for Applications Differentiation: Which of the following is correct?",
            "options": [
                "Option A for Applications Differentiation",
                "Option B for Applications Differentiation (Correct)",
                "Option C for Applications Differentiation",
                "Option D for Applications Differentiation"
            ],
            "correctIndex": 1,
            "explanation": "This is an auto-generated dummy explanation for Applications Differentiation."
        },
        {
            "id": 49,
            "question": "Dummy Question 49 for Applications Differentiation: Which of the following is correct?",
            "options": [
                "Option A for Applications Differentiation",
                "Option B for Applications Differentiation (Correct)",
                "Option C for Applications Differentiation",
                "Option D for Applications Differentiation"
            ],
            "correctIndex": 1,
            "explanation": "This is an auto-generated dummy explanation for Applications Differentiation."
        },
        {
            "id": 50,
            "question": "Dummy Question 50 for Applications Differentiation: Which of the following is correct?",
            "options": [
                "Option A for Applications Differentiation",
                "Option B for Applications Differentiation (Correct)",
                "Option C for Applications Differentiation",
                "Option D for Applications Differentiation"
            ],
            "correctIndex": 1,
            "explanation": "This is an auto-generated dummy explanation for Applications Differentiation."
        }
    ]
}